{
    "/combat_monsters/alligator": {
        "hrid": "/combat_monsters/alligator",
        "name": "Sherlock",
        "combatDetails": {
            "combatStyleHrid": "/combat_styles/slash",
            "currentHitpoints": 300,
            "maxHitpoints": 300,
            "currentManapoints": 300,
            "maxManapoints": 300,
            "stabAccuracyRating": 30,
            "slashAccuracyRating": 30,
            "smashAccuracyRating": 30,
            "stabMaxDamage": 37.1,
            "slashMaxDamage": 37.1,
            "smashMaxDamage": 37.1,
            "stabEvasionRating": 36.4,
            "slashEvasionRating": 36.4,
            "smashEvasionRating": 36.4,
            "staminaLevel": 20,
            "intelligenceLevel": 20,
            "attackLevel": 20,
            "powerLevel": 25,
            "defenseLevel": 16,
            "combatStats": {
                "attackInterval": 3500000000,
                "stabAccuracy": 0,
                "slashAccuracy": 0,
                "smashAccuracy": 0,
                "stabDamage": 0.06,
                "slashDamage": 0.06,
                "smashDamage": 0.06,
                "stabEvasion": 0.4,
                "slashEvasion": 0.4,
                "smashEvasion": 0.4,
                "armor": 0,
                "lifeSteal": 0,
                "HPRegen": 0,
                "MPRegen": 0,
                "dropRate": 0,
                "foodSlots": 0,
                "drinkSlots": 0
            }
        },
        "abilities": [{ "abilityHrid": "/abilities/scratch", "level": 10 }],
        "dropTable": [
            {
                "itemHrid": "/items/coin",
                "dropRate": 1,
                "minCount": 50,
                "maxCount": 250
            },
            {
                "itemHrid": "/items/blueberry",
                "dropRate": 0.1,
                "minCount": 1,
                "maxCount": 6
            },
            {
                "itemHrid": "/items/blackberry",
                "dropRate": 0.05,
                "minCount": 1,
                "maxCount": 4
            },
            {
                "itemHrid": "/items/apple",
                "dropRate": 0.3,
                "minCount": 1,
                "maxCount": 5
            },
            {
                "itemHrid": "/items/orange",
                "dropRate": 0.15,
                "minCount": 1,
                "maxCount": 3
            },
            {
                "itemHrid": "/items/gator_vest",
                "dropRate": 0.003,
                "minCount": 1,
                "maxCount": 1
            },
            {
                "itemHrid": "/items/swamp_essence",
                "dropRate": 0.6,
                "minCount": 4,
                "maxCount": 12
            },
            {
                "itemHrid": "/items/scratch",
                "dropRate": 0.01,
                "minCount": 1,
                "maxCount": 1
            }
        ]
    },
    "/combat_monsters/black_bear": {
        "hrid": "/combat_monsters/black_bear",
        "name": "Black Bear",
        "combatDetails": {
            "combatStyleHrid": "/combat_styles/stab",
            "currentHitpoints": 1300,
            "maxHitpoints": 1300,
            "currentManapoints": 1300,
            "maxManapoints": 1300,
            "stabAccuracyRating": 150,
            "slashAccuracyRating": 150,
            "smashAccuracyRating": 150,
            "stabMaxDamage": 150,
            "slashMaxDamage": 150,
            "smashMaxDamage": 150,
            "stabEvasionRating": 169,
            "slashEvasionRating": 130,
            "smashEvasionRating": 130,
            "staminaLevel": 120,
            "intelligenceLevel": 120,
            "attackLevel": 140,
            "powerLevel": 140,
            "defenseLevel": 120,
            "combatStats": {
                "attackInterval": 3000000000,
                "stabAccuracy": 0,
                "slashAccuracy": 0,
                "smashAccuracy": 0,
                "stabDamage": 0,
                "slashDamage": 0,
                "smashDamage": 0,
                "stabEvasion": 0.3,
                "slashEvasion": 0,
                "smashEvasion": 0,
                "armor": 0,
                "lifeSteal": 0,
                "HPRegen": 0,
                "MPRegen": 0,
                "dropRate": 0,
                "foodSlots": 0,
                "drinkSlots": 0
            }
        },
        "abilities": [{ "abilityHrid": "/abilities/frenzy", "level": 4 }],
        "dropTable": [
            {
                "itemHrid": "/items/coin",
                "dropRate": 1,
                "minCount": 340,
                "maxCount": 1700
            },
            {
                "itemHrid": "/items/mooberry",
                "dropRate": 0.1,
                "minCount": 1,
                "maxCount": 4
            },
            {
                "itemHrid": "/items/marsberry",
                "dropRate": 0.15,
                "minCount": 1,
                "maxCount": 4
            },
            {
                "itemHrid": "/items/spaceberry",
                "dropRate": 0.05,
                "minCount": 1,
                "maxCount": 4
            },
            {
                "itemHrid": "/items/black_tea_leaf",
                "dropRate": 0.3,
                "minCount": 1,
                "maxCount": 3
            },
            {
                "itemHrid": "/items/red_tea_leaf",
                "dropRate": 0.3,
                "minCount": 1,
                "maxCount": 2
            },
            {
                "itemHrid": "/items/emp_tea_leaf",
                "dropRate": 0.15,
                "minCount": 1,
                "maxCount": 1
            },
            {
                "itemHrid": "/items/black_bear_fluff",
                "dropRate": 0.002,
                "minCount": 1,
                "maxCount": 1
            },
            {
                "itemHrid": "/items/bear_essence",
                "dropRate": 0.4,
                "minCount": 2,
                "maxCount": 6
            },
            {
                "itemHrid": "/items/frenzy",
                "dropRate": 0.0006,
                "minCount": 1,
                "maxCount": 1
            }
        ]
    },
    "/combat_monsters/crab": {
        "hrid": "/combat_monsters/crab",
        "name": "I Pinch",
        "combatDetails": {
            "combatStyleHrid": "/combat_styles/smash",
            "currentHitpoints": 400,
            "maxHitpoints": 400,
            "currentManapoints": 400,
            "maxManapoints": 400,
            "stabAccuracyRating": 35,
            "slashAccuracyRating": 35,
            "smashAccuracyRating": 35,
            "stabMaxDamage": 40,
            "slashMaxDamage": 40,
            "smashMaxDamage": 40,
            "stabEvasionRating": 50,
            "slashEvasionRating": 70,
            "smashEvasionRating": 40,
            "staminaLevel": 30,
            "intelligenceLevel": 30,
            "attackLevel": 25,
            "powerLevel": 30,
            "defenseLevel": 40,
            "combatStats": {
                "attackInterval": 3500000000,
                "stabAccuracy": 0,
                "slashAccuracy": 0,
                "smashAccuracy": 0,
                "stabDamage": 0,
                "slashDamage": 0,
                "smashDamage": 0,
                "stabEvasion": 0,
                "slashEvasion": 0.4,
                "smashEvasion": -0.2,
                "armor": 0,
                "lifeSteal": 0,
                "HPRegen": 0,
                "MPRegen": 0,
                "dropRate": 0,
                "foodSlots": 0,
                "drinkSlots": 0
            }
        },
        "abilities": [{ "abilityHrid": "/abilities/smack", "level": 5 }],
        "dropTable": [
            {
                "itemHrid": "/items/coin",
                "dropRate": 1,
                "minCount": 60,
                "maxCount": 300
            },
            {
                "itemHrid": "/items/orange",
                "dropRate": 0.15,
                "minCount": 1,
                "maxCount": 5
            },
            {
                "itemHrid": "/items/plum",
                "dropRate": 0.05,
                "minCount": 1,
                "maxCount": 3
            },
            {
                "itemHrid": "/items/crab_pincer",
                "dropRate": 0.005,
                "minCount": 1,
                "maxCount": 1
            },
            {
                "itemHrid": "/items/aqua_essence",
                "dropRate": 0.4,
                "minCount": 2,
                "maxCount": 6
            },
            {
                "itemHrid": "/items/smack",
                "dropRate": 0.01,
                "minCount": 1,
                "maxCount": 1
            }
        ]
    },
    "/combat_monsters/eye": {
        "hrid": "/combat_monsters/eye",
        "name": "Eye",
        "combatDetails": {
            "combatStyleHrid": "/combat_styles/slash",
            "currentHitpoints": 990,
            "maxHitpoints": 990,
            "currentManapoints": 990,
            "maxManapoints": 990,
            "stabAccuracyRating": 99,
            "slashAccuracyRating": 99,
            "smashAccuracyRating": 99,
            "stabMaxDamage": 99,
            "slashMaxDamage": 99,
            "smashMaxDamage": 99,
            "stabEvasionRating": 74.25,
            "slashEvasionRating": 99,
            "smashEvasionRating": 99,
            "staminaLevel": 89,
            "intelligenceLevel": 89,
            "attackLevel": 89,
            "powerLevel": 89,
            "defenseLevel": 89,
            "combatStats": {
                "attackInterval": 2800000000,
                "stabAccuracy": 0,
                "slashAccuracy": 0,
                "smashAccuracy": 0,
                "stabDamage": 0,
                "slashDamage": 0,
                "smashDamage": 0,
                "stabEvasion": -0.25,
                "slashEvasion": 0,
                "smashEvasion": 0,
                "armor": 0,
                "lifeSteal": 0,
                "HPRegen": 0,
                "MPRegen": 0,
                "dropRate": 0,
                "foodSlots": 0,
                "drinkSlots": 0
            }
        },
        "abilities": [{ "abilityHrid": "/abilities/precision", "level": 1 }],
        "dropTable": [
            {
                "itemHrid": "/items/coin",
                "dropRate": 1,
                "minCount": 200,
                "maxCount": 1000
            },
            {
                "itemHrid": "/items/azure_cheese",
                "dropRate": 0.1,
                "minCount": 1,
                "maxCount": 2
            },
            {
                "itemHrid": "/items/burble_cheese",
                "dropRate": 0.1,
                "minCount": 1,
                "maxCount": 2
            },
            {
                "itemHrid": "/items/crimson_cheese",
                "dropRate": 0.1,
                "minCount": 1,
                "maxCount": 2
            },
            {
                "itemHrid": "/items/strawberry",
                "dropRate": 0.1,
                "minCount": 1,
                "maxCount": 6
            },
            {
                "itemHrid": "/items/mooberry",
                "dropRate": 0.1,
                "minCount": 1,
                "maxCount": 6
            },
            {
                "itemHrid": "/items/marsberry",
                "dropRate": 0.1,
                "minCount": 1,
                "maxCount": 6
            },
            {
                "itemHrid": "/items/plum",
                "dropRate": 0.1,
                "minCount": 1,
                "maxCount": 5
            },
            {
                "itemHrid": "/items/peach",
                "dropRate": 0.15,
                "minCount": 1,
                "maxCount": 5
            },
            {
                "itemHrid": "/items/dragon_fruit",
                "dropRate": 0.05,
                "minCount": 1,
                "maxCount": 5
            },
            {
                "itemHrid": "/items/burble_tea_leaf",
                "dropRate": 0.45,
                "minCount": 1,
                "maxCount": 3
            },
            {
                "itemHrid": "/items/moolong_tea_leaf",
                "dropRate": 0.6,
                "minCount": 1,
                "maxCount": 3
            },
            {
                "itemHrid": "/items/red_tea_leaf",
                "dropRate": 0.3,
                "minCount": 1,
                "maxCount": 3
            },
            {
                "itemHrid": "/items/eyessence",
                "dropRate": 1,
                "minCount": 1,
                "maxCount": 1
            },
            {
                "itemHrid": "/items/precision",
                "dropRate": 0.001,
                "minCount": 1,
                "maxCount": 1
            }
        ]
    },
    "/combat_monsters/eyes": {
        "hrid": "/combat_monsters/eyes",
        "name": "Eyes",
        "combatDetails": {
            "combatStyleHrid": "/combat_styles/slash",
            "currentHitpoints": 1110,
            "maxHitpoints": 1110,
            "currentManapoints": 1110,
            "maxManapoints": 1110,
            "stabAccuracyRating": 111,
            "slashAccuracyRating": 111,
            "smashAccuracyRating": 111,
            "stabMaxDamage": 111,
            "slashMaxDamage": 111,
            "smashMaxDamage": 111,
            "stabEvasionRating": 83.25,
            "slashEvasionRating": 111,
            "smashEvasionRating": 111,
            "staminaLevel": 101,
            "intelligenceLevel": 101,
            "attackLevel": 101,
            "powerLevel": 101,
            "defenseLevel": 101,
            "combatStats": {
                "attackInterval": 2800000000,
                "stabAccuracy": 0,
                "slashAccuracy": 0,
                "smashAccuracy": 0,
                "stabDamage": 0,
                "slashDamage": 0,
                "smashDamage": 0,
                "stabEvasion": -0.25,
                "slashEvasion": 0,
                "smashEvasion": 0,
                "armor": 0,
                "lifeSteal": 0,
                "HPRegen": 0,
                "MPRegen": 0,
                "dropRate": 0,
                "foodSlots": 0,
                "drinkSlots": 0
            }
        },
        "abilities": [{ "abilityHrid": "/abilities/precision", "level": 1 }],
        "dropTable": [
            {
                "itemHrid": "/items/coin",
                "dropRate": 1,
                "minCount": 240,
                "maxCount": 1200
            },
            {
                "itemHrid": "/items/burble_tea_leaf",
                "dropRate": 0.15,
                "minCount": 1,
                "maxCount": 1
            },
            {
                "itemHrid": "/items/moolong_tea_leaf",
                "dropRate": 0.2,
                "minCount": 1,
                "maxCount": 1
            },
            {
                "itemHrid": "/items/red_tea_leaf",
                "dropRate": 0.1,
                "minCount": 1,
                "maxCount": 1
            },
            {
                "itemHrid": "/items/goggles",
                "dropRate": 0.0005,
                "minCount": 1,
                "maxCount": 1
            },
            {
                "itemHrid": "/items/eyessence",
                "dropRate": 1,
                "minCount": 2,
                "maxCount": 2
            },
            {
                "itemHrid": "/items/precision",
                "dropRate": 0.0015,
                "minCount": 1,
                "maxCount": 1
            }
        ]
    },
    "/combat_monsters/fly": {
        "hrid": "/combat_monsters/fly",
        "name": "Fly",
        "combatDetails": {
            "combatStyleHrid": "/combat_styles/smash",
            "currentHitpoints": 30,
            "maxHitpoints": 30,
            "currentManapoints": 30,
            "maxManapoints": 30,
            "stabAccuracyRating": 11,
            "slashAccuracyRating": 11,
            "smashAccuracyRating": 7.699999999999999,
            "stabMaxDamage": 11,
            "slashMaxDamage": 11,
            "smashMaxDamage": 7.699999999999999,
            "stabEvasionRating": 11,
            "slashEvasionRating": 11,
            "smashEvasionRating": 11,
            "staminaLevel": -7,
            "intelligenceLevel": -7,
            "attackLevel": 1,
            "powerLevel": 1,
            "defenseLevel": 1,
            "combatStats": {
                "attackInterval": 4000000000,
                "stabAccuracy": 0,
                "slashAccuracy": 0,
                "smashAccuracy": -0.3,
                "stabDamage": 0,
                "slashDamage": 0,
                "smashDamage": -0.3,
                "stabEvasion": 0,
                "slashEvasion": 0,
                "smashEvasion": 0,
                "armor": 0,
                "lifeSteal": 0,
                "HPRegen": 0,
                "MPRegen": 0,
                "dropRate": 0,
                "foodSlots": 0,
                "drinkSlots": 0
            }
        },
        "abilities": [],
        "dropTable": [
            {
                "itemHrid": "/items/coin",
                "dropRate": 1,
                "minCount": 8,
                "maxCount": 40
            }
        ]
    },
    "/combat_monsters/frog": {
        "hrid": "/combat_monsters/frog",
        "name": "Frogger",
        "combatDetails": {
            "combatStyleHrid": "/combat_styles/smash",
            "currentHitpoints": 150,
            "maxHitpoints": 150,
            "currentManapoints": 150,
            "maxManapoints": 150,
            "stabAccuracyRating": 25,
            "slashAccuracyRating": 25,
            "smashAccuracyRating": 25,
            "stabMaxDamage": 20,
            "slashMaxDamage": 20,
            "smashMaxDamage": 20,
            "stabEvasionRating": 25,
            "slashEvasionRating": 25,
            "smashEvasionRating": 25,
            "staminaLevel": 5,
            "intelligenceLevel": 5,
            "attackLevel": 15,
            "powerLevel": 10,
            "defenseLevel": 15,
            "combatStats": {
                "attackInterval": 3200000000,
                "stabAccuracy": 0,
                "slashAccuracy": 0,
                "smashAccuracy": 0,
                "stabDamage": 0,
                "slashDamage": 0,
                "smashDamage": 0,
                "stabEvasion": 0,
                "slashEvasion": 0,
                "smashEvasion": 0,
                "armor": 0,
                "lifeSteal": 0,
                "HPRegen": 0,
                "MPRegen": 0,
                "dropRate": 0,
                "foodSlots": 0,
                "drinkSlots": 0
            }
        },
        "abilities": [{ "abilityHrid": "/abilities/smack", "level": 1 }],
        "dropTable": [
            {
                "itemHrid": "/items/coin",
                "dropRate": 1,
                "minCount": 24,
                "maxCount": 120
            },
            {
                "itemHrid": "/items/egg",
                "dropRate": 0.3,
                "minCount": 1,
                "maxCount": 2
            },
            {
                "itemHrid": "/items/green_tea_leaf",
                "dropRate": 0.4,
                "minCount": 1,
                "maxCount": 3
            },
            {
                "itemHrid": "/items/black_tea_leaf",
                "dropRate": 0.2,
                "minCount": 1,
                "maxCount": 3
            },
            {
                "itemHrid": "/items/swamp_essence",
                "dropRate": 0.4,
                "minCount": 1,
                "maxCount": 3
            },
            {
                "itemHrid": "/items/smack",
                "dropRate": 0.007,
                "minCount": 1,
                "maxCount": 1
            }
        ]
    },
    "/combat_monsters/gobo_slashy": {
        "hrid": "/combat_monsters/gobo_slashy",
        "name": "Slashy",
        "combatDetails": {
            "combatStyleHrid": "/combat_styles/slash",
            "currentHitpoints": 800,
            "maxHitpoints": 800,
            "currentManapoints": 300,
            "maxManapoints": 300,
            "stabAccuracyRating": 50,
            "slashAccuracyRating": 95,
            "smashAccuracyRating": 50,
            "stabMaxDamage": 50,
            "slashMaxDamage": 95,
            "smashMaxDamage": 50,
            "stabEvasionRating": 70,
            "slashEvasionRating": 70,
            "smashEvasionRating": 70,
            "staminaLevel": 70,
            "intelligenceLevel": 20,
            "attackLevel": 40,
            "powerLevel": 40,
            "defenseLevel": 60,
            "combatStats": {
                "attackInterval": 3300000000,
                "stabAccuracy": 0,
                "slashAccuracy": 0.9,
                "smashAccuracy": 0,
                "stabDamage": 0,
                "slashDamage": 0.9,
                "smashDamage": 0,
                "stabEvasion": 0,
                "slashEvasion": 0,
                "smashEvasion": 0,
                "armor": 0,
                "lifeSteal": 0,
                "HPRegen": 0,
                "MPRegen": 0,
                "dropRate": 0,
                "foodSlots": 0,
                "drinkSlots": 0
            }
        },
        "abilities": [{ "abilityHrid": "/abilities/cleave", "level": 1 }],
        "dropTable": [
            {
                "itemHrid": "/items/coin",
                "dropRate": 1,
                "minCount": 160,
                "maxCount": 800
            },
            {
                "itemHrid": "/items/blackberry",
                "dropRate": 0.1,
                "minCount": 1,
                "maxCount": 6
            },
            {
                "itemHrid": "/items/strawberry",
                "dropRate": 0.15,
                "minCount": 1,
                "maxCount": 6
            },
            {
                "itemHrid": "/items/mooberry",
                "dropRate": 0.05,
                "minCount": 1,
                "maxCount": 5
            },
            {
                "itemHrid": "/items/gobo_slasher",
                "dropRate": 0.001,
                "minCount": 1,
                "maxCount": 1
            },
            {
                "itemHrid": "/items/gobo_essence",
                "dropRate": 0.5,
                "minCount": 3,
                "maxCount": 9
            },
            {
                "itemHrid": "/items/black_tea_leaf",
                "dropRate": 0.2,
                "minCount": 1,
                "maxCount": 2
            },
            {
                "itemHrid": "/items/burble_tea_leaf",
                "dropRate": 0.2,
                "minCount": 1,
                "maxCount": 2
            },
            {
                "itemHrid": "/items/moolong_tea_leaf",
                "dropRate": 0.1,
                "minCount": 1,
                "maxCount": 2
            },
            {
                "itemHrid": "/items/cleave",
                "dropRate": 0.001,
                "minCount": 1,
                "maxCount": 1
            }
        ]
    },
    "/combat_monsters/gobo_smashy": {
        "hrid": "/combat_monsters/gobo_smashy",
        "name": "Smashy",
        "combatDetails": {
            "combatStyleHrid": "/combat_styles/smash",
            "currentHitpoints": 800,
            "maxHitpoints": 800,
            "currentManapoints": 300,
            "maxManapoints": 300,
            "stabAccuracyRating": 50,
            "slashAccuracyRating": 50,
            "smashAccuracyRating": 55.00000000000001,
            "stabMaxDamage": 55,
            "slashMaxDamage": 55,
            "smashMaxDamage": 145.75,
            "stabEvasionRating": 70,
            "slashEvasionRating": 70,
            "smashEvasionRating": 70,
            "staminaLevel": 70,
            "intelligenceLevel": 20,
            "attackLevel": 40,
            "powerLevel": 45,
            "defenseLevel": 60,
            "combatStats": {
                "attackInterval": 3700000000,
                "stabAccuracy": 0,
                "slashAccuracy": 0,
                "smashAccuracy": 0.1,
                "stabDamage": 0,
                "slashDamage": 0,
                "smashDamage": 1.65,
                "stabEvasion": 0,
                "slashEvasion": 0,
                "smashEvasion": 0,
                "armor": 0,
                "lifeSteal": 0,
                "HPRegen": 0,
                "MPRegen": 0,
                "dropRate": 0,
                "foodSlots": 0,
                "drinkSlots": 0
            }
        },
        "abilities": [{ "abilityHrid": "/abilities/berserk", "level": 1 }],
        "dropTable": [
            {
                "itemHrid": "/items/coin",
                "dropRate": 1,
                "minCount": 160,
                "maxCount": 800
            },
            {
                "itemHrid": "/items/orange",
                "dropRate": 0.1,
                "minCount": 1,
                "maxCount": 6
            },
            {
                "itemHrid": "/items/plum",
                "dropRate": 0.15,
                "minCount": 1,
                "maxCount": 6
            },
            {
                "itemHrid": "/items/peach",
                "dropRate": 0.05,
                "minCount": 1,
                "maxCount": 5
            },
            {
                "itemHrid": "/items/green_tea_leaf",
                "dropRate": 0.2,
                "minCount": 1,
                "maxCount": 2
            },
            {
                "itemHrid": "/items/burble_tea_leaf",
                "dropRate": 0.2,
                "minCount": 1,
                "maxCount": 2
            },
            {
                "itemHrid": "/items/moolong_tea_leaf",
                "dropRate": 0.1,
                "minCount": 1,
                "maxCount": 2
            },
            {
                "itemHrid": "/items/gobo_smasher",
                "dropRate": 0.001,
                "minCount": 1,
                "maxCount": 1
            },
            {
                "itemHrid": "/items/gobo_essence",
                "dropRate": 0.5,
                "minCount": 3,
                "maxCount": 9
            },
            {
                "itemHrid": "/items/berserk",
                "dropRate": 0.001,
                "minCount": 1,
                "maxCount": 1
            }
        ]
    },
    "/combat_monsters/gobo_stabby": {
        "hrid": "/combat_monsters/gobo_stabby",
        "name": "Stabby",
        "combatDetails": {
            "combatStyleHrid": "/combat_styles/stab",
            "currentHitpoints": 800,
            "maxHitpoints": 800,
            "currentManapoints": 300,
            "maxManapoints": 300,
            "stabAccuracyRating": 150,
            "slashAccuracyRating": 50,
            "smashAccuracyRating": 50,
            "stabMaxDamage": 44,
            "slashMaxDamage": 40,
            "smashMaxDamage": 40,
            "stabEvasionRating": 70,
            "slashEvasionRating": 70,
            "smashEvasionRating": 70,
            "staminaLevel": 70,
            "intelligenceLevel": 20,
            "attackLevel": 40,
            "powerLevel": 30,
            "defenseLevel": 60,
            "combatStats": {
                "attackInterval": 2500000000,
                "stabAccuracy": 2,
                "slashAccuracy": 0,
                "smashAccuracy": 0,
                "stabDamage": 0.1,
                "slashDamage": 0,
                "smashDamage": 0,
                "stabEvasion": 0,
                "slashEvasion": 0,
                "smashEvasion": 0,
                "armor": 0,
                "lifeSteal": 0,
                "HPRegen": 0,
                "MPRegen": 0,
                "dropRate": 0,
                "foodSlots": 0,
                "drinkSlots": 0
            }
        },
        "abilities": [{ "abilityHrid": "/abilities/pierce", "level": 1 }],
        "dropTable": [
            {
                "itemHrid": "/items/coin",
                "dropRate": 1,
                "minCount": 160,
                "maxCount": 800
            },
            {
                "itemHrid": "/items/burble_milk",
                "dropRate": 0.15,
                "minCount": 2,
                "maxCount": 10
            },
            {
                "itemHrid": "/items/crimson_milk",
                "dropRate": 0.05,
                "minCount": 2,
                "maxCount": 10
            },
            {
                "itemHrid": "/items/black_tea_leaf",
                "dropRate": 0.2,
                "minCount": 1,
                "maxCount": 2
            },
            {
                "itemHrid": "/items/burble_tea_leaf",
                "dropRate": 0.2,
                "minCount": 1,
                "maxCount": 2
            },
            {
                "itemHrid": "/items/moolong_tea_leaf",
                "dropRate": 0.1,
                "minCount": 1,
                "maxCount": 2
            },
            {
                "itemHrid": "/items/gobo_stabber",
                "dropRate": 0.001,
                "minCount": 1,
                "maxCount": 1
            },
            {
                "itemHrid": "/items/gobo_essence",
                "dropRate": 0.5,
                "minCount": 3,
                "maxCount": 9
            },
            {
                "itemHrid": "/items/pierce",
                "dropRate": 0.0015,
                "minCount": 1,
                "maxCount": 1
            }
        ]
    },
    "/combat_monsters/grizzly_bear": {
        "hrid": "/combat_monsters/grizzly_bear",
        "name": "Grizzly Bear",
        "combatDetails": {
            "combatStyleHrid": "/combat_styles/slash",
            "currentHitpoints": 1400,
            "maxHitpoints": 1400,
            "currentManapoints": 1400,
            "maxManapoints": 1400,
            "stabAccuracyRating": 160,
            "slashAccuracyRating": 160,
            "smashAccuracyRating": 160,
            "stabMaxDamage": 160,
            "slashMaxDamage": 160,
            "smashMaxDamage": 160,
            "stabEvasionRating": 140,
            "slashEvasionRating": 182,
            "smashEvasionRating": 140,
            "staminaLevel": 130,
            "intelligenceLevel": 130,
            "attackLevel": 150,
            "powerLevel": 150,
            "defenseLevel": 130,
            "combatStats": {
                "attackInterval": 3000000000,
                "stabAccuracy": 0,
                "slashAccuracy": 0,
                "smashAccuracy": 0,
                "stabDamage": 0,
                "slashDamage": 0,
                "smashDamage": 0,
                "stabEvasion": 0,
                "slashEvasion": 0.3,
                "smashEvasion": 0,
                "armor": 0,
                "lifeSteal": 0,
                "HPRegen": 0,
                "MPRegen": 0,
                "dropRate": 0,
                "foodSlots": 0,
                "drinkSlots": 0
            }
        },
        "abilities": [{ "abilityHrid": "/abilities/frenzy", "level": 7 }],
        "dropTable": [
            {
                "itemHrid": "/items/coin",
                "dropRate": 1,
                "minCount": 380,
                "maxCount": 1900
            },
            {
                "itemHrid": "/items/mooberry",
                "dropRate": 0.1,
                "minCount": 1,
                "maxCount": 6
            },
            {
                "itemHrid": "/items/marsberry",
                "dropRate": 0.15,
                "minCount": 1,
                "maxCount": 6
            },
            {
                "itemHrid": "/items/spaceberry",
                "dropRate": 0.05,
                "minCount": 1,
                "maxCount": 6
            },
            {
                "itemHrid": "/items/burble_tea_leaf",
                "dropRate": 0.3,
                "minCount": 1,
                "maxCount": 3
            },
            {
                "itemHrid": "/items/red_tea_leaf",
                "dropRate": 0.3,
                "minCount": 1,
                "maxCount": 2
            },
            {
                "itemHrid": "/items/emp_tea_leaf",
                "dropRate": 0.15,
                "minCount": 1,
                "maxCount": 1
            },
            {
                "itemHrid": "/items/grizzly_bear_fluff",
                "dropRate": 0.002,
                "minCount": 1,
                "maxCount": 1
            },
            {
                "itemHrid": "/items/bear_essence",
                "dropRate": 0.5,
                "minCount": 3,
                "maxCount": 9
            },
            {
                "itemHrid": "/items/frenzy",
                "dropRate": 0.0008,
                "minCount": 1,
                "maxCount": 1
            }
        ]
    },
    "/combat_monsters/gummy_bear": {
        "hrid": "/combat_monsters/gummy_bear",
        "name": "Gummy Bear",
        "combatDetails": {
            "combatStyleHrid": "/combat_styles/smash",
            "currentHitpoints": 1200,
            "maxHitpoints": 1200,
            "currentManapoints": 1200,
            "maxManapoints": 1200,
            "stabAccuracyRating": 150,
            "slashAccuracyRating": 150,
            "smashAccuracyRating": 150,
            "stabMaxDamage": 90,
            "slashMaxDamage": 90,
            "smashMaxDamage": 90,
            "stabEvasionRating": 110,
            "slashEvasionRating": 110,
            "smashEvasionRating": 143,
            "staminaLevel": 110,
            "intelligenceLevel": 110,
            "attackLevel": 140,
            "powerLevel": 80,
            "defenseLevel": 100,
            "combatStats": {
                "attackInterval": 2600000000,
                "stabAccuracy": 0,
                "slashAccuracy": 0,
                "smashAccuracy": 0,
                "stabDamage": 0,
                "slashDamage": 0,
                "smashDamage": 0,
                "stabEvasion": 0,
                "slashEvasion": 0,
                "smashEvasion": 0.3,
                "armor": 0,
                "lifeSteal": 0,
                "HPRegen": 0,
                "MPRegen": 0,
                "dropRate": 0,
                "foodSlots": 0,
                "drinkSlots": 0
            }
        },
        "abilities": [{ "abilityHrid": "/abilities/frenzy", "level": 1 }],
        "dropTable": [
            {
                "itemHrid": "/items/sugar",
                "dropRate": 1,
                "minCount": 50,
                "maxCount": 250
            },
            {
                "itemHrid": "/items/apple_gummy",
                "dropRate": 0.5,
                "minCount": 1,
                "maxCount": 1
            },
            {
                "itemHrid": "/items/orange_gummy",
                "dropRate": 0.5,
                "minCount": 1,
                "maxCount": 1
            },
            {
                "itemHrid": "/items/plum_gummy",
                "dropRate": 0.5,
                "minCount": 1,
                "maxCount": 1
            },
            {
                "itemHrid": "/items/peach_gummy",
                "dropRate": 0.5,
                "minCount": 1,
                "maxCount": 1
            },
            {
                "itemHrid": "/items/dragon_fruit_gummy",
                "dropRate": 0.5,
                "minCount": 1,
                "maxCount": 1
            },
            {
                "itemHrid": "/items/bear_essence",
                "dropRate": 0.4,
                "minCount": 1,
                "maxCount": 3
            },
            {
                "itemHrid": "/items/frenzy",
                "dropRate": 0.0003,
                "minCount": 1,
                "maxCount": 1
            }
        ]
    },
    "/combat_monsters/nom_nom": {
        "hrid": "/combat_monsters/nom_nom",
        "name": "Nom Nom",
        "combatDetails": {
            "combatStyleHrid": "/combat_styles/stab",
            "currentHitpoints": 480,
            "maxHitpoints": 480,
            "currentManapoints": 480,
            "maxManapoints": 480,
            "stabAccuracyRating": 44,
            "slashAccuracyRating": 44,
            "smashAccuracyRating": 55,
            "stabMaxDamage": 55,
            "slashMaxDamage": 55,
            "smashMaxDamage": 55,
            "stabEvasionRating": 55,
            "slashEvasionRating": 55,
            "smashEvasionRating": 55,
            "staminaLevel": 38,
            "intelligenceLevel": 38,
            "attackLevel": 45,
            "powerLevel": 45,
            "defenseLevel": 45,
            "combatStats": {
                "attackInterval": 3200000000,
                "stabAccuracy": -0.2,
                "slashAccuracy": -0.2,
                "smashAccuracy": 0,
                "stabDamage": 0,
                "slashDamage": 0,
                "smashDamage": 0,
                "stabEvasion": 0,
                "slashEvasion": 0,
                "smashEvasion": 0,
                "armor": 0,
                "lifeSteal": 0,
                "HPRegen": 0,
                "MPRegen": 0,
                "dropRate": 0,
                "foodSlots": 0,
                "drinkSlots": 0
            }
        },
        "abilities": [{ "abilityHrid": "/abilities/pierce", "level": 1 }],
        "dropTable": [
            {
                "itemHrid": "/items/coin",
                "dropRate": 1,
                "minCount": 90,
                "maxCount": 450
            },
            {
                "itemHrid": "/items/blackberry",
                "dropRate": 0.15,
                "minCount": 1,
                "maxCount": 12
            },
            {
                "itemHrid": "/items/strawberry",
                "dropRate": 0.05,
                "minCount": 1,
                "maxCount": 8
            },
            {
                "itemHrid": "/items/orange",
                "dropRate": 0.15,
                "minCount": 1,
                "maxCount": 10
            },
            {
                "itemHrid": "/items/plum",
                "dropRate": 0.05,
                "minCount": 1,
                "maxCount": 6
            },
            {
                "itemHrid": "/items/green_tea_leaf",
                "dropRate": 0.3,
                "minCount": 1,
                "maxCount": 3
            },
            {
                "itemHrid": "/items/black_tea_leaf",
                "dropRate": 0.4,
                "minCount": 1,
                "maxCount": 3
            },
            {
                "itemHrid": "/items/burble_tea_leaf",
                "dropRate": 0.2,
                "minCount": 1,
                "maxCount": 3
            },
            {
                "itemHrid": "/items/aqua_essence",
                "dropRate": 0.6,
                "minCount": 4,
                "maxCount": 12
            },
            {
                "itemHrid": "/items/pierce",
                "dropRate": 0.001,
                "minCount": 1,
                "maxCount": 1
            }
        ]
    },
    "/combat_monsters/panda": {
        "hrid": "/combat_monsters/panda",
        "name": "Panda",
        "combatDetails": {
            "combatStyleHrid": "/combat_styles/smash",
            "currentHitpoints": 1600,
            "maxHitpoints": 1600,
            "currentManapoints": 1600,
            "maxManapoints": 1600,
            "stabAccuracyRating": 140,
            "slashAccuracyRating": 140,
            "smashAccuracyRating": 140,
            "stabMaxDamage": 140,
            "slashMaxDamage": 140,
            "smashMaxDamage": 140,
            "stabEvasionRating": 160,
            "slashEvasionRating": 160,
            "smashEvasionRating": 208,
            "staminaLevel": 150,
            "intelligenceLevel": 150,
            "attackLevel": 130,
            "powerLevel": 130,
            "defenseLevel": 150,
            "combatStats": {
                "attackInterval": 3500000000,
                "stabAccuracy": 0,
                "slashAccuracy": 0,
                "smashAccuracy": 0,
                "stabDamage": 0,
                "slashDamage": 0,
                "smashDamage": 0,
                "stabEvasion": 0,
                "slashEvasion": 0,
                "smashEvasion": 0.3,
                "armor": 8,
                "lifeSteal": 0,
                "HPRegen": 0,
                "MPRegen": 0,
                "dropRate": 0,
                "foodSlots": 0,
                "drinkSlots": 0
            }
        },
        "abilities": [{ "abilityHrid": "/abilities/toughness", "level": 10 }],
        "dropTable": [
            {
                "itemHrid": "/items/coin",
                "dropRate": 1,
                "minCount": 340,
                "maxCount": 1700
            },
            {
                "itemHrid": "/items/wheat",
                "dropRate": 0.3,
                "minCount": 1,
                "maxCount": 15
            },
            {
                "itemHrid": "/items/egg",
                "dropRate": 0.3,
                "minCount": 1,
                "maxCount": 15
            },
            {
                "itemHrid": "/items/peach",
                "dropRate": 0.1,
                "minCount": 1,
                "maxCount": 5
            },
            {
                "itemHrid": "/items/dragon_fruit",
                "dropRate": 0.15,
                "minCount": 1,
                "maxCount": 5
            },
            {
                "itemHrid": "/items/star_fruit",
                "dropRate": 0.05,
                "minCount": 1,
                "maxCount": 5
            },
            {
                "itemHrid": "/items/green_tea_leaf",
                "dropRate": 0.3,
                "minCount": 1,
                "maxCount": 3
            },
            {
                "itemHrid": "/items/red_tea_leaf",
                "dropRate": 0.3,
                "minCount": 1,
                "maxCount": 2
            },
            {
                "itemHrid": "/items/emp_tea_leaf",
                "dropRate": 0.15,
                "minCount": 1,
                "maxCount": 1
            },
            {
                "itemHrid": "/items/panda_fluff",
                "dropRate": 0.002,
                "minCount": 1,
                "maxCount": 1
            },
            {
                "itemHrid": "/items/bear_essence",
                "dropRate": 0.4,
                "minCount": 2,
                "maxCount": 6
            },
            {
                "itemHrid": "/items/toughness",
                "dropRate": 0.002,
                "minCount": 1,
                "maxCount": 1
            }
        ]
    },
    "/combat_monsters/polar_bear": {
        "hrid": "/combat_monsters/polar_bear",
        "name": "Polar Bear",
        "combatDetails": {
            "combatStyleHrid": "/combat_styles/smash",
            "currentHitpoints": 1500,
            "maxHitpoints": 1500,
            "currentManapoints": 1500,
            "maxManapoints": 1500,
            "stabAccuracyRating": 170,
            "slashAccuracyRating": 170,
            "smashAccuracyRating": 170,
            "stabMaxDamage": 170,
            "slashMaxDamage": 170,
            "smashMaxDamage": 170,
            "stabEvasionRating": 150,
            "slashEvasionRating": 150,
            "smashEvasionRating": 195,
            "staminaLevel": 140,
            "intelligenceLevel": 140,
            "attackLevel": 160,
            "powerLevel": 160,
            "defenseLevel": 140,
            "combatStats": {
                "attackInterval": 3000000000,
                "stabAccuracy": 0,
                "slashAccuracy": 0,
                "smashAccuracy": 0,
                "stabDamage": 0,
                "slashDamage": 0,
                "smashDamage": 0,
                "stabEvasion": 0,
                "slashEvasion": 0,
                "smashEvasion": 0.3,
                "armor": 0,
                "lifeSteal": 0,
                "HPRegen": 0,
                "MPRegen": 0,
                "dropRate": 0,
                "foodSlots": 0,
                "drinkSlots": 0
            }
        },
        "abilities": [{ "abilityHrid": "/abilities/frenzy", "level": 10 }],
        "dropTable": [
            {
                "itemHrid": "/items/coin",
                "dropRate": 1,
                "minCount": 440,
                "maxCount": 2200
            },
            {
                "itemHrid": "/items/crimson_milk",
                "dropRate": 0.1,
                "minCount": 1,
                "maxCount": 4
            },
            {
                "itemHrid": "/items/rainbow_milk",
                "dropRate": 0.15,
                "minCount": 1,
                "maxCount": 4
            },
            {
                "itemHrid": "/items/holy_milk",
                "dropRate": 0.05,
                "minCount": 1,
                "maxCount": 4
            },
            {
                "itemHrid": "/items/moolong_tea_leaf",
                "dropRate": 0.3,
                "minCount": 1,
                "maxCount": 3
            },
            {
                "itemHrid": "/items/red_tea_leaf",
                "dropRate": 0.3,
                "minCount": 1,
                "maxCount": 2
            },
            {
                "itemHrid": "/items/emp_tea_leaf",
                "dropRate": 0.15,
                "minCount": 1,
                "maxCount": 1
            },
            {
                "itemHrid": "/items/polar_bear_fluff",
                "dropRate": 0.002,
                "minCount": 1,
                "maxCount": 1
            },
            {
                "itemHrid": "/items/bear_essence",
                "dropRate": 0.6,
                "minCount": 4,
                "maxCount": 12
            },
            {
                "itemHrid": "/items/frenzy",
                "dropRate": 0.001,
                "minCount": 1,
                "maxCount": 1
            }
        ]
    },
    "/combat_monsters/rat": {
        "hrid": "/combat_monsters/rat",
        "name": "Jerry",
        "combatDetails": {
            "combatStyleHrid": "/combat_styles/stab",
            "currentHitpoints": 60,
            "maxHitpoints": 60,
            "currentManapoints": 100,
            "maxManapoints": 100,
            "stabAccuracyRating": 14,
            "slashAccuracyRating": 14,
            "smashAccuracyRating": 14,
            "stabMaxDamage": 14,
            "slashMaxDamage": 14,
            "smashMaxDamage": 14,
            "stabEvasionRating": 14,
            "slashEvasionRating": 14,
            "smashEvasionRating": 14,
            "staminaLevel": -4,
            "intelligenceLevel": 0,
            "attackLevel": 4,
            "powerLevel": 4,
            "defenseLevel": 4,
            "combatStats": {
                "attackInterval": 3500000000,
                "stabAccuracy": 0,
                "slashAccuracy": 0,
                "smashAccuracy": 0,
                "stabDamage": 0,
                "slashDamage": 0,
                "smashDamage": 0,
                "stabEvasion": 0,
                "slashEvasion": 0,
                "smashEvasion": 0,
                "armor": 0,
                "lifeSteal": 0,
                "HPRegen": 0,
                "MPRegen": 0,
                "dropRate": 0,
                "foodSlots": 0,
                "drinkSlots": 0
            }
        },
        "abilities": [{ "abilityHrid": "/abilities/poke", "level": 1 }],
        "dropTable": [
            {
                "itemHrid": "/items/coin",
                "dropRate": 1,
                "minCount": 10,
                "maxCount": 50
            },
            {
                "itemHrid": "/items/wheat",
                "dropRate": 0.3,
                "minCount": 1,
                "maxCount": 3
            },
            {
                "itemHrid": "/items/sugar",
                "dropRate": 0.3,
                "minCount": 1,
                "maxCount": 6
            },
            {
                "itemHrid": "/items/cheese",
                "dropRate": 0.2,
                "minCount": 1,
                "maxCount": 1
            },
            {
                "itemHrid": "/items/verdant_cheese",
                "dropRate": 0.1,
                "minCount": 1,
                "maxCount": 1
            },
            {
                "itemHrid": "/items/azure_cheese",
                "dropRate": 0.05,
                "minCount": 1,
                "maxCount": 1
            },
            {
                "itemHrid": "/items/poke",
                "dropRate": 0.005,
                "minCount": 1,
                "maxCount": 1
            }
        ]
    },
    "/combat_monsters/sea_snail": {
        "hrid": "/combat_monsters/sea_snail",
        "name": "Gary",
        "combatDetails": {
            "combatStyleHrid": "/combat_styles/smash",
            "currentHitpoints": 350,
            "maxHitpoints": 350,
            "currentManapoints": 350,
            "maxManapoints": 350,
            "stabAccuracyRating": 32,
            "slashAccuracyRating": 32,
            "smashAccuracyRating": 32,
            "stabMaxDamage": 32,
            "slashMaxDamage": 32,
            "smashMaxDamage": 32,
            "stabEvasionRating": 38,
            "slashEvasionRating": 53.199999999999996,
            "smashEvasionRating": 30.400000000000002,
            "staminaLevel": 25,
            "intelligenceLevel": 25,
            "attackLevel": 22,
            "powerLevel": 22,
            "defenseLevel": 28,
            "combatStats": {
                "attackInterval": 4000000000,
                "stabAccuracy": 0,
                "slashAccuracy": 0,
                "smashAccuracy": 0,
                "stabDamage": 0,
                "slashDamage": 0,
                "smashDamage": 0,
                "stabEvasion": 0,
                "slashEvasion": 0.4,
                "smashEvasion": -0.2,
                "armor": 0,
                "lifeSteal": 0,
                "HPRegen": 0,
                "MPRegen": 0,
                "dropRate": 0,
                "foodSlots": 0,
                "drinkSlots": 0
            }
        },
        "abilities": [{ "abilityHrid": "/abilities/toughness", "level": 1 }],
        "dropTable": [
            {
                "itemHrid": "/items/coin",
                "dropRate": 1,
                "minCount": 56,
                "maxCount": 280
            },
            {
                "itemHrid": "/items/wheat",
                "dropRate": 0.3,
                "minCount": 1,
                "maxCount": 10
            },
            {
                "itemHrid": "/items/snail_shell",
                "dropRate": 0.006,
                "minCount": 1,
                "maxCount": 1
            },
            {
                "itemHrid": "/items/green_tea_leaf",
                "dropRate": 0.3,
                "minCount": 1,
                "maxCount": 2
            },
            {
                "itemHrid": "/items/black_tea_leaf",
                "dropRate": 0.4,
                "minCount": 1,
                "maxCount": 2
            },
            {
                "itemHrid": "/items/burble_tea_leaf",
                "dropRate": 0.2,
                "minCount": 1,
                "maxCount": 2
            },
            {
                "itemHrid": "/items/aqua_essence",
                "dropRate": 0.4,
                "minCount": 1,
                "maxCount": 3
            },
            {
                "itemHrid": "/items/toughness",
                "dropRate": 0.001,
                "minCount": 1,
                "maxCount": 1
            }
        ]
    },
    "/combat_monsters/skunk": {
        "hrid": "/combat_monsters/skunk",
        "name": "Skunk",
        "combatDetails": {
            "combatStyleHrid": "/combat_styles/slash",
            "currentHitpoints": 80,
            "maxHitpoints": 80,
            "currentManapoints": 100,
            "maxManapoints": 100,
            "stabAccuracyRating": 18,
            "slashAccuracyRating": 18,
            "smashAccuracyRating": 18,
            "stabMaxDamage": 18,
            "slashMaxDamage": 18,
            "smashMaxDamage": 18,
            "stabEvasionRating": 18,
            "slashEvasionRating": 18,
            "smashEvasionRating": 18,
            "staminaLevel": -2,
            "intelligenceLevel": 0,
            "attackLevel": 8,
            "powerLevel": 8,
            "defenseLevel": 8,
            "combatStats": {
                "attackInterval": 3500000000,
                "stabAccuracy": 0,
                "slashAccuracy": 0,
                "smashAccuracy": 0,
                "stabDamage": 0,
                "slashDamage": 0,
                "smashDamage": 0,
                "stabEvasion": 0,
                "slashEvasion": 0,
                "smashEvasion": 0,
                "armor": 0,
                "lifeSteal": 0,
                "HPRegen": 0,
                "MPRegen": 0,
                "dropRate": 0,
                "foodSlots": 0,
                "drinkSlots": 0
            }
        },
        "abilities": [{ "abilityHrid": "/abilities/scratch", "level": 1 }],
        "dropTable": [
            {
                "itemHrid": "/items/coin",
                "dropRate": 1,
                "minCount": 14,
                "maxCount": 70
            },
            {
                "itemHrid": "/items/blueberry",
                "dropRate": 0.2,
                "minCount": 1,
                "maxCount": 5
            },
            {
                "itemHrid": "/items/green_tea_leaf",
                "dropRate": 0.2,
                "minCount": 1,
                "maxCount": 3
            },
            {
                "itemHrid": "/items/scratch",
                "dropRate": 0.005,
                "minCount": 1,
                "maxCount": 1
            }
        ]
    },
    "/combat_monsters/slimy": {
        "hrid": "/combat_monsters/slimy",
        "name": "Slimy",
        "combatDetails": {
            "combatStyleHrid": "/combat_styles/smash",
            "currentHitpoints": 120,
            "maxHitpoints": 120,
            "currentManapoints": 120,
            "maxManapoints": 120,
            "stabAccuracyRating": 19,
            "slashAccuracyRating": 19,
            "smashAccuracyRating": 19,
            "stabMaxDamage": 22,
            "slashMaxDamage": 22,
            "smashMaxDamage": 22,
            "stabEvasionRating": 20,
            "slashEvasionRating": 20,
            "smashEvasionRating": 20,
            "staminaLevel": 2,
            "intelligenceLevel": 2,
            "attackLevel": 9,
            "powerLevel": 12,
            "defenseLevel": 10,
            "combatStats": {
                "attackInterval": 3500000000,
                "stabAccuracy": 0,
                "slashAccuracy": 0,
                "smashAccuracy": 0,
                "stabDamage": 0,
                "slashDamage": 0,
                "smashDamage": 0,
                "stabEvasion": 0,
                "slashEvasion": 0,
                "smashEvasion": 0,
                "armor": 0,
                "lifeSteal": 0,
                "HPRegen": 0,
                "MPRegen": 0,
                "dropRate": 0,
                "foodSlots": 0,
                "drinkSlots": 0
            }
        },
        "abilities": [{ "abilityHrid": "/abilities/smack", "level": 1 }],
        "dropTable": [
            {
                "itemHrid": "/items/coin",
                "dropRate": 1,
                "minCount": 20,
                "maxCount": 100
            },
            {
                "itemHrid": "/items/apple",
                "dropRate": 0.2,
                "minCount": 1,
                "maxCount": 4
            },
            {
                "itemHrid": "/items/green_tea_leaf",
                "dropRate": 0.2,
                "minCount": 1,
                "maxCount": 4
            },
            {
                "itemHrid": "/items/smack",
                "dropRate": 0.005,
                "minCount": 1,
                "maxCount": 1
            }
        ]
    },
    "/combat_monsters/snake": {
        "hrid": "/combat_monsters/snake",
        "name": "Thnake",
        "combatDetails": {
            "combatStyleHrid": "/combat_styles/stab",
            "currentHitpoints": 200,
            "maxHitpoints": 200,
            "currentManapoints": 200,
            "maxManapoints": 200,
            "stabAccuracyRating": 24,
            "slashAccuracyRating": 24,
            "smashAccuracyRating": 24,
            "stabMaxDamage": 26,
            "slashMaxDamage": 26,
            "smashMaxDamage": 26,
            "stabEvasionRating": 28,
            "slashEvasionRating": 19.599999999999998,
            "smashEvasionRating": 28,
            "staminaLevel": 10,
            "intelligenceLevel": 10,
            "attackLevel": 14,
            "powerLevel": 16,
            "defenseLevel": 18,
            "combatStats": {
                "attackInterval": 3200000000,
                "stabAccuracy": 0,
                "slashAccuracy": 0,
                "smashAccuracy": 0,
                "stabDamage": 0,
                "slashDamage": 0,
                "smashDamage": 0,
                "stabEvasion": 0,
                "slashEvasion": -0.3,
                "smashEvasion": 0,
                "armor": 0,
                "lifeSteal": 0,
                "HPRegen": 0,
                "MPRegen": 0,
                "dropRate": 0,
                "foodSlots": 0,
                "drinkSlots": 0
            }
        },
        "abilities": [{ "abilityHrid": "/abilities/poke", "level": 5 }],
        "dropTable": [
            {
                "itemHrid": "/items/coin",
                "dropRate": 1,
                "minCount": 32,
                "maxCount": 160
            },
            {
                "itemHrid": "/items/egg",
                "dropRate": 0.3,
                "minCount": 1,
                "maxCount": 4
            },
            {
                "itemHrid": "/items/snake_fang",
                "dropRate": 0.04,
                "minCount": 1,
                "maxCount": 1
            },
            {
                "itemHrid": "/items/swamp_essence",
                "dropRate": 0.4,
                "minCount": 2,
                "maxCount": 6
            },
            {
                "itemHrid": "/items/poke",
                "dropRate": 0.008,
                "minCount": 1,
                "maxCount": 1
            }
        ]
    },
    "/combat_monsters/swampy": {
        "hrid": "/combat_monsters/swampy",
        "name": "Swampy",
        "combatDetails": {
            "combatStyleHrid": "/combat_styles/smash",
            "currentHitpoints": 260,
            "maxHitpoints": 260,
            "currentManapoints": 260,
            "maxManapoints": 260,
            "stabAccuracyRating": 28,
            "slashAccuracyRating": 28,
            "smashAccuracyRating": 28,
            "stabMaxDamage": 26,
            "slashMaxDamage": 26,
            "smashMaxDamage": 26,
            "stabEvasionRating": 32,
            "slashEvasionRating": 32,
            "smashEvasionRating": 22.4,
            "staminaLevel": 16,
            "intelligenceLevel": 16,
            "attackLevel": 18,
            "powerLevel": 16,
            "defenseLevel": 22,
            "combatStats": {
                "attackInterval": 3000000000,
                "stabAccuracy": 0,
                "slashAccuracy": 0,
                "smashAccuracy": 0,
                "stabDamage": 0,
                "slashDamage": 0,
                "smashDamage": 0,
                "stabEvasion": 0,
                "slashEvasion": 0,
                "smashEvasion": -0.3,
                "armor": 0,
                "lifeSteal": 0,
                "HPRegen": 0,
                "MPRegen": 0,
                "dropRate": 0,
                "foodSlots": 0,
                "drinkSlots": 0
            }
        },
        "abilities": [{ "abilityHrid": "/abilities/sweep", "level": 1 }],
        "dropTable": [
            {
                "itemHrid": "/items/coin",
                "dropRate": 1,
                "minCount": 44,
                "maxCount": 220
            },
            {
                "itemHrid": "/items/blueberry",
                "dropRate": 0.3,
                "minCount": 1,
                "maxCount": 6
            },
            {
                "itemHrid": "/items/blackberry",
                "dropRate": 0.15,
                "minCount": 1,
                "maxCount": 4
            },
            {
                "itemHrid": "/items/apple",
                "dropRate": 0.1,
                "minCount": 1,
                "maxCount": 5
            },
            {
                "itemHrid": "/items/orange",
                "dropRate": 0.05,
                "minCount": 1,
                "maxCount": 3
            },
            {
                "itemHrid": "/items/green_tea_leaf",
                "dropRate": 0.4,
                "minCount": 1,
                "maxCount": 4
            },
            {
                "itemHrid": "/items/black_tea_leaf",
                "dropRate": 0.2,
                "minCount": 1,
                "maxCount": 4
            },
            {
                "itemHrid": "/items/swamp_essence",
                "dropRate": 0.6,
                "minCount": 3,
                "maxCount": 9
            },
            {
                "itemHrid": "/items/sweep",
                "dropRate": 0.002,
                "minCount": 1,
                "maxCount": 1
            }
        ]
    },
    "/combat_monsters/turtle": {
        "hrid": "/combat_monsters/turtle",
        "name": "Turuto",
        "combatDetails": {
            "combatStyleHrid": "/combat_styles/smash",
            "currentHitpoints": 700,
            "maxHitpoints": 700,
            "currentManapoints": 600,
            "maxManapoints": 600,
            "stabAccuracyRating": 50,
            "slashAccuracyRating": 50,
            "smashAccuracyRating": 50,
            "stabMaxDamage": 65,
            "slashMaxDamage": 65,
            "smashMaxDamage": 65,
            "stabEvasionRating": 65,
            "slashEvasionRating": 91,
            "smashEvasionRating": 52,
            "staminaLevel": 60,
            "intelligenceLevel": 50,
            "attackLevel": 40,
            "powerLevel": 55,
            "defenseLevel": 55,
            "combatStats": {
                "attackInterval": 3500000000,
                "stabAccuracy": 0,
                "slashAccuracy": 0,
                "smashAccuracy": 0,
                "stabDamage": 0,
                "slashDamage": 0,
                "smashDamage": 0,
                "stabEvasion": 0,
                "slashEvasion": 0.4,
                "smashEvasion": -0.2,
                "armor": 0,
                "lifeSteal": 0,
                "HPRegen": 0,
                "MPRegen": 0,
                "dropRate": 0,
                "foodSlots": 0,
                "drinkSlots": 0
            }
        },
        "abilities": [{ "abilityHrid": "/abilities/toughness", "level": 10 }],
        "dropTable": [
            {
                "itemHrid": "/items/coin",
                "dropRate": 1,
                "minCount": 120,
                "maxCount": 600
            },
            {
                "itemHrid": "/items/egg",
                "dropRate": 0.2,
                "minCount": 1,
                "maxCount": 10
            },
            {
                "itemHrid": "/items/orange",
                "dropRate": 0.1,
                "minCount": 1,
                "maxCount": 4
            },
            {
                "itemHrid": "/items/plum",
                "dropRate": 0.15,
                "minCount": 1,
                "maxCount": 5
            },
            {
                "itemHrid": "/items/peach",
                "dropRate": 0.05,
                "minCount": 1,
                "maxCount": 3
            },
            {
                "itemHrid": "/items/turtle_shell",
                "dropRate": 0.004,
                "minCount": 1,
                "maxCount": 1
            },
            {
                "itemHrid": "/items/aqua_essence",
                "dropRate": 0.6,
                "minCount": 3,
                "maxCount": 15
            },
            {
                "itemHrid": "/items/toughness",
                "dropRate": 0.0015,
                "minCount": 1,
                "maxCount": 1
            }
        ]
    },
    "/combat_monsters/vampire": {
        "hrid": "/combat_monsters/vampire",
        "name": "Vampire",
        "combatDetails": {
            "combatStyleHrid": "/combat_styles/stab",
            "currentHitpoints": 2000,
            "maxHitpoints": 2000,
            "currentManapoints": 2000,
            "maxManapoints": 2000,
            "stabAccuracyRating": 260,
            "slashAccuracyRating": 260,
            "smashAccuracyRating": 260,
            "stabMaxDamage": 200,
            "slashMaxDamage": 200,
            "smashMaxDamage": 200,
            "stabEvasionRating": 260,
            "slashEvasionRating": 260,
            "smashEvasionRating": 260,
            "staminaLevel": 190,
            "intelligenceLevel": 190,
            "attackLevel": 250,
            "powerLevel": 190,
            "defenseLevel": 250,
            "combatStats": {
                "attackInterval": 2800000000,
                "stabAccuracy": 0,
                "slashAccuracy": 0,
                "smashAccuracy": 0,
                "stabDamage": 0,
                "slashDamage": 0,
                "smashDamage": 0,
                "stabEvasion": 0,
                "slashEvasion": 0,
                "smashEvasion": 0,
                "armor": 0,
                "lifeSteal": 0.02,
                "HPRegen": 0,
                "MPRegen": 0,
                "dropRate": 0,
                "foodSlots": 0,
                "drinkSlots": 0
            }
        },
        "abilities": [{ "abilityHrid": "/abilities/vampirism", "level": 1 }],
        "dropTable": [
            {
                "itemHrid": "/items/coin",
                "dropRate": 1,
                "minCount": 600,
                "maxCount": 3000
            },
            {
                "itemHrid": "/items/red_tea_leaf",
                "dropRate": 0.2,
                "minCount": 1,
                "maxCount": 2
            },
            {
                "itemHrid": "/items/emp_tea_leaf",
                "dropRate": 0.2,
                "minCount": 1,
                "maxCount": 2
            },
            {
                "itemHrid": "/items/twilight_essence",
                "dropRate": 0.5,
                "minCount": 2,
                "maxCount": 6
            },
            {
                "itemHrid": "/items/vampire_fang",
                "dropRate": 0.001,
                "minCount": 1,
                "maxCount": 1
            },
            {
                "itemHrid": "/items/vampirism",
                "dropRate": 0.0008,
                "minCount": 1,
                "maxCount": 1
            }
        ]
    },
    "/combat_monsters/veyes": {
        "hrid": "/combat_monsters/veyes",
        "name": "Veyes",
        "combatDetails": {
            "combatStyleHrid": "/combat_styles/slash",
            "currentHitpoints": 1230,
            "maxHitpoints": 1230,
            "currentManapoints": 1230,
            "maxManapoints": 1230,
            "stabAccuracyRating": 123,
            "slashAccuracyRating": 123,
            "smashAccuracyRating": 123,
            "stabMaxDamage": 123,
            "slashMaxDamage": 123,
            "smashMaxDamage": 123,
            "stabEvasionRating": 92.25,
            "slashEvasionRating": 123,
            "smashEvasionRating": 123,
            "staminaLevel": 113,
            "intelligenceLevel": 113,
            "attackLevel": 113,
            "powerLevel": 113,
            "defenseLevel": 113,
            "combatStats": {
                "attackInterval": 2800000000,
                "stabAccuracy": 0,
                "slashAccuracy": 0,
                "smashAccuracy": 0,
                "stabDamage": 0,
                "slashDamage": 0,
                "smashDamage": 0,
                "stabEvasion": -0.25,
                "slashEvasion": 0,
                "smashEvasion": 0,
                "armor": 0,
                "lifeSteal": 0,
                "HPRegen": 0,
                "MPRegen": 0,
                "dropRate": 0,
                "foodSlots": 0,
                "drinkSlots": 0
            }
        },
        "abilities": [{ "abilityHrid": "/abilities/precision", "level": 1 }],
        "dropTable": [
            {
                "itemHrid": "/items/coin",
                "dropRate": 1,
                "minCount": 280,
                "maxCount": 1400
            },
            {
                "itemHrid": "/items/burble_tea_leaf",
                "dropRate": 0.15,
                "minCount": 1,
                "maxCount": 2
            },
            {
                "itemHrid": "/items/moolong_tea_leaf",
                "dropRate": 0.2,
                "minCount": 1,
                "maxCount": 2
            },
            {
                "itemHrid": "/items/red_tea_leaf",
                "dropRate": 0.1,
                "minCount": 1,
                "maxCount": 2
            },
            {
                "itemHrid": "/items/magnifying_glass",
                "dropRate": 0.0005,
                "minCount": 1,
                "maxCount": 1
            },
            {
                "itemHrid": "/items/eyessence",
                "dropRate": 1,
                "minCount": 5,
                "maxCount": 5
            },
            {
                "itemHrid": "/items/precision",
                "dropRate": 0.002,
                "minCount": 1,
                "maxCount": 1
            }
        ]
    },
    "/combat_monsters/werewolf": {
        "hrid": "/combat_monsters/werewolf",
        "name": "Werewolf",
        "combatDetails": {
            "combatStyleHrid": "/combat_styles/slash",
            "currentHitpoints": 2400,
            "maxHitpoints": 2400,
            "currentManapoints": 2400,
            "maxManapoints": 2400,
            "stabAccuracyRating": 230,
            "slashAccuracyRating": 230,
            "smashAccuracyRating": 230,
            "stabMaxDamage": 230,
            "slashMaxDamage": 230,
            "smashMaxDamage": 230,
            "stabEvasionRating": 210,
            "slashEvasionRating": 210,
            "smashEvasionRating": 210,
            "staminaLevel": 230,
            "intelligenceLevel": 230,
            "attackLevel": 220,
            "powerLevel": 220,
            "defenseLevel": 200,
            "combatStats": {
                "attackInterval": 2800000000,
                "stabAccuracy": 0,
                "slashAccuracy": 0,
                "smashAccuracy": 0,
                "stabDamage": 0,
                "slashDamage": 0,
                "smashDamage": 0,
                "stabEvasion": 0,
                "slashEvasion": 0,
                "smashEvasion": 0,
                "armor": 0,
                "lifeSteal": 0,
                "HPRegen": 0,
                "MPRegen": 0,
                "dropRate": 0,
                "foodSlots": 0,
                "drinkSlots": 0
            }
        },
        "abilities": [
            { "abilityHrid": "/abilities/berserk", "level": 10 },
            { "abilityHrid": "/abilities/maim", "level": 10 }
        ],
        "dropTable": [
            {
                "itemHrid": "/items/coin",
                "dropRate": 1,
                "minCount": 750,
                "maxCount": 3750
            },
            {
                "itemHrid": "/items/red_tea_leaf",
                "dropRate": 0.2,
                "minCount": 1,
                "maxCount": 2
            },
            {
                "itemHrid": "/items/emp_tea_leaf",
                "dropRate": 0.2,
                "minCount": 1,
                "maxCount": 2
            },
            {
                "itemHrid": "/items/twilight_essence",
                "dropRate": 0.6,
                "minCount": 3,
                "maxCount": 9
            },
            {
                "itemHrid": "/items/werewolf_claw",
                "dropRate": 0.001,
                "minCount": 1,
                "maxCount": 1
            },
            {
                "itemHrid": "/items/berserk",
                "dropRate": 0.002,
                "minCount": 1,
                "maxCount": 1
            },
            {
                "itemHrid": "/items/maim",
                "dropRate": 0.0008,
                "minCount": 1,
                "maxCount": 1
            }
        ]
    },
    "/combat_monsters/zombie": {
        "hrid": "/combat_monsters/zombie",
        "name": "Zombie",
        "combatDetails": {
            "combatStyleHrid": "/combat_styles/slash",
            "currentHitpoints": 1700,
            "maxHitpoints": 1700,
            "currentManapoints": 1700,
            "maxManapoints": 1700,
            "stabAccuracyRating": 190,
            "slashAccuracyRating": 190,
            "smashAccuracyRating": 190,
            "stabMaxDamage": 200,
            "slashMaxDamage": 200,
            "smashMaxDamage": 200,
            "stabEvasionRating": 200,
            "slashEvasionRating": 200,
            "smashEvasionRating": 200,
            "staminaLevel": 160,
            "intelligenceLevel": 160,
            "attackLevel": 180,
            "powerLevel": 190,
            "defenseLevel": 190,
            "combatStats": {
                "attackInterval": 3200000000,
                "stabAccuracy": 0,
                "slashAccuracy": 0,
                "smashAccuracy": 0,
                "stabDamage": 0,
                "slashDamage": 0,
                "smashDamage": 0,
                "stabEvasion": 0,
                "slashEvasion": 0,
                "smashEvasion": 0,
                "armor": 0,
                "lifeSteal": 0,
                "HPRegen": 0,
                "MPRegen": 0,
                "dropRate": 0,
                "foodSlots": 0,
                "drinkSlots": 0
            }
        },
        "abilities": [
            { "abilityHrid": "/abilities/toughness", "level": 10 },
            { "abilityHrid": "/abilities/maim", "level": 1 }
        ],
        "dropTable": [
            {
                "itemHrid": "/items/coin",
                "dropRate": 1,
                "minCount": 500,
                "maxCount": 2500
            },
            {
                "itemHrid": "/items/green_tea_leaf",
                "dropRate": 0.3,
                "minCount": 1,
                "maxCount": 5
            },
            {
                "itemHrid": "/items/black_tea_leaf",
                "dropRate": 0.3,
                "minCount": 1,
                "maxCount": 5
            },
            {
                "itemHrid": "/items/burble_tea_leaf",
                "dropRate": 0.3,
                "minCount": 1,
                "maxCount": 4
            },
            {
                "itemHrid": "/items/moolong_tea_leaf",
                "dropRate": 0.3,
                "minCount": 1,
                "maxCount": 4
            },
            {
                "itemHrid": "/items/red_tea_leaf",
                "dropRate": 0.4,
                "minCount": 1,
                "maxCount": 3
            },
            {
                "itemHrid": "/items/emp_tea_leaf",
                "dropRate": 0.4,
                "minCount": 1,
                "maxCount": 3
            },
            {
                "itemHrid": "/items/twilight_essence",
                "dropRate": 0.4,
                "minCount": 1,
                "maxCount": 3
            },
            {
                "itemHrid": "/items/toughness",
                "dropRate": 0.002,
                "minCount": 1,
                "maxCount": 1
            },
            {
                "itemHrid": "/items/maim",
                "dropRate": 0.0005,
                "minCount": 1,
                "maxCount": 1
            }
        ]
    }
}
